daba/Mongo.py
daba/__init__.py
tests/__init__.py
tests/Database/Mongo.py
tests/Database/__init__.py
daba-1.0.2.dist-info/LICENSE
daba-1.0.2.dist-info/METADATA
daba-1.0.2.dist-info/WHEEL
daba-1.0.2.dist-info/top_level.txt
daba-1.0.2.dist-info/RECORD
