Metadata-Version: 2.1
Name: daba
Version: 1.0.2
Summary: daba by Klivolks.
Home-page: https://github.com/klivolks/DaBa
Author: Vishnu Prakash
Author-email: vishnu@klivolks.com
Classifier: Development Status :: 5 - Production/Stable
Classifier: Intended Audience :: Developers
Classifier: License :: OSI Approved :: GNU General Public License v3 (GPLv3)
Classifier: Programming Language :: Python :: 3.9
Classifier: Programming Language :: Python :: 3.11
Classifier: Programming Language :: Python :: 3.13
License-File: LICENSE
